{
  "project_info": {
    "project_number": "62948119848",
    "project_id": "plantcodeteste",
    "storage_bucket": "plantcodeteste.firebasestorage.app"
  },
  "client": [
    {
      "client_info": {
        "mobilesdk_app_id": "1:62948119848:android:aefe5a7c4fd1c094d2ac1d",
        "android_client_info": {
          "package_name": "com.example.plantcodedata"
        }
      },
      "oauth_client": [],
      "api_key": [
        {
          "current_key": "AIzaSyCnbZa8RRilYrBAD9J6oPcJwZ3GdD81VfI"
        }
      ],
      "services": {
        "appinvite_service": {
          "other_platform_oauth_client": []
        }
      }
    }
  ],
  "configuration_version": "1"
}